{
    "data": [
        {
            "title": "Местоимения",
            "forms": [
                {
                    "label": "Они не видели его. (didn't see)",
                    "answers": [
                        "They didn't see him.",
                        "They didn't see him",
                        "They did not see him"
                    ]
                },
                {
                    "label": "Она скажет им? (Will tell)",
                    "answers": [
                        "Will she tell them?",
                        "Will she tell them"
                    ]
                },
                {
                    "label": "Ты поможешь ей? (Will help)",
                    "answers": [
                        "Will you help her?",
                        "Will you help her"
                    ]
                },
                {
                    "label": "Они не помогают нам. ( don't help )",
                    "answers": [
                        "They don't help us.",
                        "They don't help us"
                    ]
                },
                {
                    "label": "Мы сказали ей. ( told )",
                    "answers": [
                        "We told her.",
                        "We told her"
                    ]
                },
                {
                    "label": "Я вижу это. (see)",
                    "answers": [
                        "I see it.",
                        "I see it"
                    ]
                },
                {
                    "label": "Вы помогли нам. (helped)",
                    "answers": [
                        "You helped us.",
                        "You helped us"
                    ]
                },
                {
                    "label": "Я помог тебе. (helped)",
                    "answers": [
                        "I helped you.",
                        "I helped you"
                    ]
                },
                {
                    "label": "Мы любили его. (loved)",
                    "answers": [
                        "We loved him.",
                        "We loved him"
                    ]
                },
                {
                    "label": "Ты сказал им? (Did tell)",
                    "answers": [
                        "Did you tell them?",
                        "Did you tell them"
                    ]
                }
            ]
        },
        {
            "title": "Вопросительные слова",
            "forms": [
                {
                    "label": "Что ты ешь? ( do you eat?)",
                    "answers": [
                        "What do you eat?",
                        "What do you eat"
                    ]
                },
                {
                    "label": "Что вы чувствуете? ( do you feel?)",
                    "answers": [
                        "What do you feel?",
                        "What do you feel"
                    ]
                },
                {
                    "label": "Что мы будем делать? ( will we do?)",
                    "answers": [
                        "What will we do?",
                        "What will we do"
                    ]
                },
                {
                    "label": "Кто работает в офисе? ( works in the office?)",
                    "answers": [
                        "Who works in the office?",
                        "Who works in the office"
                    ]
                },
                {
                    "label": "Где вы учитесь? (. do you study?)",
                    "answers": [
                        "Where do you study?",
                        "Where do you study"
                    ]
                },
                {
                    "label": "Когда ты придёшь? (.. will you come?)",
                    "answers": [
                        "When will you come?",
                        "When will you come"
                    ]
                },
                {
                    "label": "Почему она беспокоится? ( does she worry?)",
                    "answers": [
                        "Why does she worry?",
                        "Why does she worry"
                    ]
                },
                {
                    "label": "Как он работает? ( does he work?)",
                    "answers": [
                        "How does he work?",
                        "How does he work"
                    ]
                },
                {
                    "label": "Как это работает? ( does it work?)",
                    "answers": [
                        "How does it work?",
                        "How does it work"
                    ]
                },
                {
                    "label": "Сколько ты зарабатываешь? ( do you earn?)",
                    "answers": [
                        "How much do you earn?",
                        "How much do you earn"
                    ]
                }
            ]
        },
        {
            "title": "Указательные слова",
            "forms": [
                {
                    "label": "Мы встретились в том самом кафе.",
                    "answers": [
                        "We met in the same cafe.",
                        "We met in the same cafe"
                    ]
                },
                {
                    "label": "Я хорошо чувствую себя здесь.",
                    "answers": [
                        "I feel good here.",
                        "I feel good here"
                    ]
                },
                {
                    "label": "Он там работал.",
                    "answers": [
                        "He worked there.",
                        "He worked there"
                    ]
                },
                {
                    "label": "Я здесь работаю.",
                    "answers": [
                        "I work here.",
                        "I work here"
                    ]
                },
                {
                    "label": "Я учусь здесь.",
                    "answers": [
                        "I learn here.",
                        "I learn here"
                    ]
                },
                {
                    "label": "Ты пойдёшь туда?",
                    "answers": [
                        "Will you go there?",
                        "Will you go there?"
                    ]
                },
                {
                    "label": "Они жили в том доме.",
                    "answers": [
                        "They lived in that house.",
                        "They lived in that house"
                    ]
                },
                {
                    "label": "Она не будет работать там.",
                    "answers": [
                        "She will not work there.",
                        "She will not work there"
                    ]
                },
                {
                    "label": "Нам нужны те вещи.",
                    "answers": [
                        "We need those things.",
                        "We need those things"
                    ]
                },
                {
                    "label": "Эти цветы красивые.",
                    "answers": [
                        "These flowers are beautiful.",
                        "These flowers are beautiful"
                    ]
                }
            ]
        },
        {
            "title": "to learn",
            "forms": [
                {
                    "label": "Я учусь.",
                    "answers": [
                        "I learn.",
                        "I learn"
                    ]
                },
                {
                    "label": "Он не учится.",
                    "answers": [
                        "He does not study.",
                        "He does not study"
                    ]
                },
                {
                    "label": "Она будет учиться?",
                    "answers": [
                        "Will she study?",
                        "Will she study"
                    ]
                },
                {
                    "label": "Ты не будешь учиться.",
                    "answers": [
                        "Will you not study?",
                        "Will you not study"
                    ]
                },
                {
                    "label": "Мы учились.",
                    "answers": [
                        "We studied.",
                        "We studied"
                    ]
                },
                {
                    "label": "Они не учились.",
                    "answers": [
                        "They did not study.",
                        "They did not study"
                    ]
                },
                {
                    "label": "Они учатся.",
                    "answers": [
                        "They study.",
                        "They study"
                    ]
                },
                {
                    "label": "Мы учимся?",
                    "answers": [
                        "Will we study?",
                        "Will we study"
                    ]
                },
                {
                    "label": "Она училась?",
                    "answers": [
                        "Did she study?",
                        "Did she study"
                    ]
                }
            ]
        },
        {
            "title": "to teach",
            "forms": [
                {
                    "label": "Он не будет учить.",
                    "answers": [
                        "He will not study.",
                        "He will not study"
                    ]
                },
                {
                    "label": "Она учила?",
                    "answers": [
                        "Did she study?",
                        "Did she study"
                    ]
                },
                {
                    "label": "Я учил.",
                    "answers": [
                        "I studied.",
                        "I studied"
                    ]
                },
                {
                    "label": "Мы будем учить.",
                    "answers": [
                        "We will study.",
                        "We will study"
                    ]
                },
                {
                    "label": "Ты не учишь.",
                    "answers": [
                        "Will you not study?",
                        "Will you not study"
                    ]
                },
                {
                    "label": "Они учат?",
                    "answers": [
                        "Will they study?",
                        "Will they study"
                    ]
                },
                {
                    "label": "Я буду учить?",
                    "answers": [
                        "Will I study?",
                        "Will I study"
                    ]
                },
                {
                    "label": "Она не учила.",
                    "answers": [
                        "She did not study.",
                        "She did not study"
                    ]
                },
                {
                    "label": "Он учит.",
                    "answers": [
                        "He studies.",
                        "He studies"
                    ]
                }
            ]
        },
        {
            "title": "to work",
            "forms": [
                {
                    "label": "Он работает.",
                    "answers": [
                        "He works.",
                        "He works"
                    ]
                },
                {
                    "label": "Они не будут работать.",
                    "answers": [
                        "They will not work.",
                        "They will not work"
                    ]
                },
                {
                    "label": "Ты работаешь?",
                    "answers": [
                        "Will you work?",
                        "Will you work"
                    ]
                },
                {
                    "label": "Мы не работаем.",
                    "answers": [
                        "We do not work.",
                        "We do not work"
                    ]
                },
                {
                    "label": "Она будет работать?",
                    "answers": [
                        "Will she work?",
                        "Will she work"
                    ]
                },
                {
                    "label": "Они работали?",
                    "answers": [
                        "Did they work?",
                        "Did they work"
                    ]
                },
                {
                    "label": "Ты не работал.",
                    "answers": [
                        "Did you work?",
                        "Did you work"
                    ]
                },
                {
                    "label": "Я буду работать.",
                    "answers": [
                        "Will I work?",
                        "Will I work"
                    ]
                },
                {
                    "label": "Она работала.",
                    "answers": [
                        "She worked.",
                        "She worked"
                    ]
                }
            ]
        },
        {
            "title": "to make",
            "forms": [
                {
                    "label": "Он не сделал.",
                    "answers": [
                        "He did not make.",
                        "He did not make"
                    ]
                },
                {
                    "label": "Я не сделал.",
                    "answers": [
                        "I did not make.",
                        "I did not make"
                    ]
                },
                {
                    "label": "Они сделают?",
                    "answers": [
                        "Will they make?",
                        "Will they make"
                    ]
                },
                {
                    "label": "Мы не сделаем.",
                    "answers": [
                        "We will not make.",
                        "We will not make"
                    ]
                },
                {
                    "label": "Она сделает.",
                    "answers": [
                        "She makes.",
                        "She makes"
                    ]
                },
                {
                    "label": "Он сделал?",
                    "answers": [
                        "Did he make?",
                        "Did he make"
                    ]
                },
                {
                    "label": "Ты не сделаешь.",
                    "answers": [
                        "Will you not make?",
                        "Will you not make"
                    ]
                },
                {
                    "label": "Она не делает.",
                    "answers": [
                        "She does not make.",
                        "She does not make"
                    ]
                },
                {
                    "label": "Он сделал.",
                    "answers": [
                        "He made.",
                        "He made"
                    ]
                }
            ]
        },
        {
            "title": "to think",
            "forms": [
                {
                    "label": "Я думаю.",
                    "answers": [
                        "I think.",
                        "I think"
                    ]
                },
                {
                    "label": "Мы не думали.",
                    "answers": [
                        "We did not think.",
                        "We did not think"
                    ]
                },
                {
                    "label": "Они подумают?",
                    "answers": [
                        "Will they think?",
                        "Will they think"
                    ]
                },
                {
                    "label": "Ты думал?",
                    "answers": [
                        "Did you think?",
                        "Did you think"
                    ]
                },
                {
                    "label": "Они думали.",
                    "answers": [
                        "They thought.",
                        "They thought"
                    ]
                },
                {
                    "label": "Он не подумает.",
                    "answers": [
                        "He will not think.",
                        "He will not think"
                    ]
                },
                {
                    "label": "Она не думает.",
                    "answers": [
                        "She does not think.",
                        "She does not think"
                    ]
                },
                {
                    "label": "Мы думаем?",
                    "answers": [
                        "Will we think?",
                        "Will we think"
                    ]
                },
                {
                    "label": "Ты подумаешь.",
                    "answers": [
                        "Will you think?",
                        "Will you think"
                    ]
                }
            ]
        },
        {
            "title": "to study",
            "forms": [
                {
                    "label": "Я не изучал.",
                    "answers": [
                        "I did not study.",
                        "I did not study"
                    ]
                },
                {
                    "label": "Мы будем изучать.",
                    "answers": [
                        "We will study.",
                        "We will study"
                    ]
                },
                {
                    "label": "Они будут изучать.",
                    "answers": [
                        "They will study.",
                        "They will study"
                    ]
                },
                {
                    "label": "Ты не изучаешь.",
                    "answers": [
                        "Will you not study?",
                        "Will you not study"
                    ]
                },
                {
                    "label": "Он изучает?",
                    "answers": [
                        "Did he study?",
                        "Did he study"
                    ]
                },
                {
                    "label": "Она изучает.",
                    "answers": [
                        "She studies.",
                        "She studies"
                    ]
                },
                {
                    "label": "Они изучали?",
                    "answers": [
                        "Did they study?",
                        "Did they study"
                    ]
                },
                {
                    "label": "Мы изучали.",
                    "answers": [
                        "We studied.",
                        "We studied"
                    ]
                }
            ]
        },
        {
            "title": "to feel",
            "forms": [
                {
                    "label": "Я чувствую.",
                    "answers": [
                        "I feel.",
                        "I feel"
                    ]
                },
                {
                    "label": "Мы не чувствовали.",
                    "answers": [
                        "We did not feel.",
                        "We did not feel"
                    ]
                },
                {
                    "label": "Они чувствуют?",
                    "answers": [
                        "Will they feel?",
                        "Will they feel"
                    ]
                },
                {
                    "label": "Ты чувствуешь?",
                    "answers": [
                        "Did you feel?",
                        "Did you feel"
                    ]
                },
                {
                    "label": "Они чувствовали.",
                    "answers": [
                        "They felt.",
                        "They felt"
                    ]
                },
                {
                    "label": "Он не чувствует.",
                    "answers": [
                        "He will not feel.",
                        "He will not feel"
                    ]
                },
                {
                    "label": "Она не чувствует.",
                    "answers": [
                        "She does not feel.",
                        "She does not feel"
                    ]
                },
                {
                    "label": "Мы чувствуем?",
                    "answers": [
                        "Will we feel?",
                        "Will we feel"
                    ]
                },
                {
                    "label": "Ты чувствуешь.",
                    "answers": [
                        "Will you feel?",
                        "Will you feel"
                    ]
                }
            ]
        },
        {
            "title": "to worry",
            "forms": [
                {
                    "label": "Они будут беспокоиться?",
                    "answers": [
                        "Will they worry?",
                        "Will they worry"
                    ]
                },
                {
                    "label": "Я беспокоюсь.",
                    "answers": [
                        "I worry.",
                        "I worry"
                    ]
                },
                {
                    "label": "Мы не беспокоились.",
                    "answers": [
                        "We did not worry.",
                        "We did not worry"
                    ]
                },
                {
                    "label": "Ты будешь беспокоиться?",
                    "answers": [
                        "Will you worry?",
                        "Will you worry"
                    ]
                },
                {
                    "label": "Она не беспокоится.",
                    "answers": [
                        "She does not worry.",
                        "She does not worry"
                    ]
                },
                {
                    "label": "Они беспокоятся.",
                    "answers": [
                        "They worry.",
                        "They worry"
                    ]
                },
                {
                    "label": "Мы беспокоились.",
                    "answers": [
                        "We worried.",
                        "We worried"
                    ]
                },
                {
                    "label": "Я не буду беспокоиться.",
                    "answers": [
                        "I will not worry.",
                        "I will not worry"
                    ]
                },
                {
                    "label": "Он беспокоился?",
                    "answers": [
                        "Did he worry?",
                        "Did he worry"
                    ]
                }
            ]
        },
        {
            "title": "translate",
            "forms": [
                {
                    "label": "What do you make?",
                    "answers": [
                        "Что ты делаешь?",
                        "Что ты делаешь"
                    ]
                },
                {
                    "label": "Who studies here?",
                    "answers": [
                        "Кто здесь учится?",
                        "Кто здесь учится"
                    ]
                },
                {
                    "label": "Where do you work?",
                    "answers": [
                        "Где ты работаешь?",
                        "Где ты работаешь"
                    ]
                },
                {
                    "label": "What does he feel?",
                    "answers": [
                        "Что он чувствует?",
                        "Что он чувствует"
                    ]
                },
                {
                    "label": "Why do they worry?",
                    "answers": [
                        "Почему они беспокоятся?",
                        "Почему они беспокоятся"
                    ]
                },
                {
                    "label": "I don't worry.",
                    "answers": [
                        "Я не беспокоюсь.",
                        "Я не беспокоюсь"
                    ]
                },
                {
                    "label": "She learns it.",
                    "answers": [
                        "Она изучает.",
                        "Она изучает"
                    ]
                },
                {
                    "label": "I worked there.",
                    "answers": [
                        "Я работал там.",
                        "Я работал там"
                    ]
                },
                {
                    "label": "Did you think?",
                    "answers": [
                        "Ты думал?",
                        "Ты думал"
                    ]
                },
                {
                    "label": "He studied here.",
                    "answers": [
                        "Он изучал здесь.",
                        "Он изучал здесь"
                    ]
                },
                {
                    "label": "She will feel.",
                    "answers": [
                        "Она будет чувствовать.",
                        "Она будет чувствовать"
                    ]
                },
                {
                    "label": "We didn't teach.",
                    "answers": [
                        "Мы не учили.",
                        "Мы не учили"
                    ]
                },
                {
                    "label": "They will not worry.",
                    "answers": [
                        "Они не будут беспокояться.",
                        "Они не будут беспокояться"
                    ]
                },
                {
                    "label": "They didn't study there.",
                    "answers": [
                        "Они не изучали там.",
                        "Они не изучали там"
                    ]
                },
                {
                    "label": "I teach here.",
                    "answers": [
                        "Я учу там.",
                        "Я учу там"
                    ]
                },
                {
                    "label": "I will not work here.",
                    "answers": [
                        "Я не буду работать там.",
                        "Я не буду работать там"
                    ]
                }
            ]
        }
    ]
}